src/__init__.py
src/cli.py
src/core.py
src/exceptions.py
pdat_qrgen-0.1.0.dist-info/LICENSE
pdat_qrgen-0.1.0.dist-info/METADATA
pdat_qrgen-0.1.0.dist-info/WHEEL
pdat_qrgen-0.1.0.dist-info/entry_points.txt
pdat_qrgen-0.1.0.dist-info/RECORD
