Metadata-Version: 2.3
Name: pdat-qrgen
Version: 0.1.0
Summary: Advanced QR Code Generator with Logo Embedding
License: MIT
Author: Pavel Dat
Author-email: dats.pavel1999@gmail.com
Requires-Python: >=3.9,<4.0
Classifier: License :: OSI Approved :: MIT License
Classifier: Programming Language :: Python :: 3
Classifier: Programming Language :: Python :: 3.9
Classifier: Programming Language :: Python :: 3.10
Classifier: Programming Language :: Python :: 3.11
Classifier: Programming Language :: Python :: 3.12
Classifier: Programming Language :: Python :: 3.13
Requires-Dist: Pillow (>=10.0,<11.0)
Requires-Dist: click (>=8.1,<9.0)
Requires-Dist: qrcode (>=7.4,<8.0)
